ooolib/__init__.py
ooolib/tests/__init__.py
ooolib/tests/test_calc_cell.py
ooolib/tests/utils.py
ooolib_python-0.0.22.dist-info/LICENSE
ooolib_python-0.0.22.dist-info/METADATA
ooolib_python-0.0.22.dist-info/WHEEL
ooolib_python-0.0.22.dist-info/top_level.txt
ooolib_python-0.0.22.dist-info/RECORD
