Metadata-Version: 2.1
Name: ooolib-python
Version: 0.0.22
Summary: Package for creating OpenDocument Format(ODF) spreadsheets.
Home-page: https://github.com/zbohm/python-ooolib
Author: Joseph Colton
Author-email: joseph@colton.byuh.edu
Maintainer: Zdeněk Böhm
Maintainer-email: zdenek.bohm@nic.cz
License: MIT
Platform: UNKNOWN
Classifier: Development Status :: 5 - Production/Stable
Classifier: Programming Language :: Python :: 2.7
Classifier: Programming Language :: Python :: 3
Classifier: License :: OSI Approved :: MIT License
Classifier: Operating System :: OS Independent
